[
  {
    "_id": "93051120-e8a9-11e8-a41c-f3af534e2a1b",
    "_type": "index-pattern",
    "_source": {
      "title": "petstore-*",
      "timeFieldName": "@timestamp",
      "fields": "[{\"name\":\"@timestamp\",\"type\":\"date\",\"count\":0,\"scripted\":false,\"searchable\":true,\"aggregatable\":true,\"readFromDocValues\":true},{\"name\":\"@version\",\"type\":\"string\",\"count\":0,\"scripted\":false,\"searchable\":true,\"aggregatable\":false,\"readFromDocValues\":false},{\"name\":\"@version.keyword\",\"type\":\"string\",\"count\":0,\"scripted\":false,\"searchable\":true,\"aggregatable\":true,\"readFromDocValues\":true},{\"name\":\"_id\",\"type\":\"string\",\"count\":0,\"scripted\":false,\"searchable\":true,\"aggregatable\":true,\"readFromDocValues\":false},{\"name\":\"_index\",\"type\":\"string\",\"count\":0,\"scripted\":false,\"searchable\":true,\"aggregatable\":true,\"readFromDocValues\":false},{\"name\":\"_score\",\"type\":\"number\",\"count\":0,\"scripted\":false,\"searchable\":false,\"aggregatable\":false,\"readFromDocValues\":false},{\"name\":\"_source\",\"type\":\"_source\",\"count\":0,\"scripted\":false,\"searchable\":false,\"aggregatable\":false,\"readFromDocValues\":false},{\"name\":\"_type\",\"type\":\"string\",\"count\":0,\"scripted\":false,\"searchable\":true,\"aggregatable\":true,\"readFromDocValues\":false},{\"name\":\"agent\",\"type\":\"string\",\"count\":0,\"scripted\":false,\"searchable\":true,\"aggregatable\":false,\"readFromDocValues\":false},{\"name\":\"agent.keyword\",\"type\":\"string\",\"count\":0,\"scripted\":false,\"searchable\":true,\"aggregatable\":true,\"readFromDocValues\":true},{\"name\":\"auth\",\"type\":\"string\",\"count\":0,\"scripted\":false,\"searchable\":true,\"aggregatable\":false,\"readFromDocValues\":false},{\"name\":\"auth.keyword\",\"type\":\"string\",\"count\":0,\"scripted\":false,\"searchable\":true,\"aggregatable\":true,\"readFromDocValues\":true},{\"name\":\"beat.hostname\",\"type\":\"string\",\"count\":0,\"scripted\":false,\"searchable\":true,\"aggregatable\":false,\"readFromDocValues\":false},{\"name\":\"beat.hostname.keyword\",\"type\":\"string\",\"count\":0,\"scripted\":false,\"searchable\":true,\"aggregatable\":true,\"readFromDocValues\":true},{\"name\":\"beat.name\",\"type\":\"string\",\"count\":0,\"scripted\":false,\"searchable\":true,\"aggregatable\":false,\"readFromDocValues\":false},{\"name\":\"beat.name.keyword\",\"type\":\"string\",\"count\":0,\"scripted\":false,\"searchable\":true,\"aggregatable\":true,\"readFromDocValues\":true},{\"name\":\"beat.version\",\"type\":\"string\",\"count\":0,\"scripted\":false,\"searchable\":true,\"aggregatable\":false,\"readFromDocValues\":false},{\"name\":\"beat.version.keyword\",\"type\":\"string\",\"count\":0,\"scripted\":false,\"searchable\":true,\"aggregatable\":true,\"readFromDocValues\":true},{\"name\":\"build\",\"type\":\"string\",\"count\":0,\"scripted\":false,\"searchable\":true,\"aggregatable\":false,\"readFromDocValues\":false},{\"name\":\"build.keyword\",\"type\":\"string\",\"count\":0,\"scripted\":false,\"searchable\":true,\"aggregatable\":true,\"readFromDocValues\":true},{\"name\":\"bytes\",\"type\":\"number\",\"count\":0,\"scripted\":false,\"searchable\":true,\"aggregatable\":true,\"readFromDocValues\":true},{\"name\":\"clientip\",\"type\":\"string\",\"count\":0,\"scripted\":false,\"searchable\":true,\"aggregatable\":false,\"readFromDocValues\":false},{\"name\":\"clientip.keyword\",\"type\":\"string\",\"count\":0,\"scripted\":false,\"searchable\":true,\"aggregatable\":true,\"readFromDocValues\":true},{\"name\":\"device\",\"type\":\"string\",\"count\":0,\"scripted\":false,\"searchable\":true,\"aggregatable\":false,\"readFromDocValues\":false},{\"name\":\"device.keyword\",\"type\":\"string\",\"count\":0,\"scripted\":false,\"searchable\":true,\"aggregatable\":true,\"readFromDocValues\":true},{\"name\":\"geoip.city_name\",\"type\":\"string\",\"count\":0,\"scripted\":false,\"searchable\":true,\"aggregatable\":false,\"readFromDocValues\":false},{\"name\":\"geoip.city_name.keyword\",\"type\":\"string\",\"count\":0,\"scripted\":false,\"searchable\":true,\"aggregatable\":true,\"readFromDocValues\":true},{\"name\":\"geoip.continent_code\",\"type\":\"string\",\"count\":0,\"scripted\":false,\"searchable\":true,\"aggregatable\":false,\"readFromDocValues\":false},{\"name\":\"geoip.continent_code.keyword\",\"type\":\"string\",\"count\":0,\"scripted\":false,\"searchable\":true,\"aggregatable\":true,\"readFromDocValues\":true},{\"name\":\"geoip.country_code2\",\"type\":\"string\",\"count\":0,\"scripted\":false,\"searchable\":true,\"aggregatable\":false,\"readFromDocValues\":false},{\"name\":\"geoip.country_code2.keyword\",\"type\":\"string\",\"count\":0,\"scripted\":false,\"searchable\":true,\"aggregatable\":true,\"readFromDocValues\":true},{\"name\":\"geoip.country_code3\",\"type\":\"string\",\"count\":0,\"scripted\":false,\"searchable\":true,\"aggregatable\":false,\"readFromDocValues\":false},{\"name\":\"geoip.country_code3.keyword\",\"type\":\"string\",\"count\":0,\"scripted\":false,\"searchable\":true,\"aggregatable\":true,\"readFromDocValues\":true},{\"name\":\"geoip.country_name\",\"type\":\"string\",\"count\":0,\"scripted\":false,\"searchable\":true,\"aggregatable\":false,\"readFromDocValues\":false},{\"name\":\"geoip.country_name.keyword\",\"type\":\"string\",\"count\":0,\"scripted\":false,\"searchable\":true,\"aggregatable\":true,\"readFromDocValues\":true},{\"name\":\"geoip.dma_code\",\"type\":\"number\",\"count\":0,\"scripted\":false,\"searchable\":true,\"aggregatable\":true,\"readFromDocValues\":true},{\"name\":\"geoip.ip\",\"type\":\"string\",\"count\":0,\"scripted\":false,\"searchable\":true,\"aggregatable\":false,\"readFromDocValues\":false},{\"name\":\"geoip.ip.keyword\",\"type\":\"string\",\"count\":0,\"scripted\":false,\"searchable\":true,\"aggregatable\":true,\"readFromDocValues\":true},{\"name\":\"geoip.latitude\",\"type\":\"number\",\"count\":0,\"scripted\":false,\"searchable\":true,\"aggregatable\":true,\"readFromDocValues\":true},{\"name\":\"geoip.location\",\"type\":\"geo_point\",\"count\":0,\"scripted\":false,\"searchable\":true,\"aggregatable\":true,\"readFromDocValues\":true},{\"name\":\"geoip.longitude\",\"type\":\"number\",\"count\":0,\"scripted\":false,\"searchable\":true,\"aggregatable\":true,\"readFromDocValues\":true},{\"name\":\"geoip.postal_code\",\"type\":\"string\",\"count\":0,\"scripted\":false,\"searchable\":true,\"aggregatable\":false,\"readFromDocValues\":false},{\"name\":\"geoip.postal_code.keyword\",\"type\":\"string\",\"count\":0,\"scripted\":false,\"searchable\":true,\"aggregatable\":true,\"readFromDocValues\":true},{\"name\":\"geoip.region_code\",\"type\":\"string\",\"count\":0,\"scripted\":false,\"searchable\":true,\"aggregatable\":false,\"readFromDocValues\":false},{\"name\":\"geoip.region_code.keyword\",\"type\":\"string\",\"count\":0,\"scripted\":false,\"searchable\":true,\"aggregatable\":true,\"readFromDocValues\":true},{\"name\":\"geoip.region_name\",\"type\":\"string\",\"count\":0,\"scripted\":false,\"searchable\":true,\"aggregatable\":false,\"readFromDocValues\":false},{\"name\":\"geoip.region_name.keyword\",\"type\":\"string\",\"count\":0,\"scripted\":false,\"searchable\":true,\"aggregatable\":true,\"readFromDocValues\":true},{\"name\":\"geoip.timezone\",\"type\":\"string\",\"count\":0,\"scripted\":false,\"searchable\":true,\"aggregatable\":false,\"readFromDocValues\":false},{\"name\":\"geoip.timezone.keyword\",\"type\":\"string\",\"count\":0,\"scripted\":false,\"searchable\":true,\"aggregatable\":true,\"readFromDocValues\":true},{\"name\":\"host.name\",\"type\":\"string\",\"count\":0,\"scripted\":false,\"searchable\":true,\"aggregatable\":false,\"readFromDocValues\":false},{\"name\":\"host.name.keyword\",\"type\":\"string\",\"count\":0,\"scripted\":false,\"searchable\":true,\"aggregatable\":true,\"readFromDocValues\":true},{\"name\":\"httprequest\",\"type\":\"string\",\"count\":0,\"scripted\":false,\"searchable\":true,\"aggregatable\":false,\"readFromDocValues\":false},{\"name\":\"httprequest.keyword\",\"type\":\"string\",\"count\":0,\"scripted\":false,\"searchable\":true,\"aggregatable\":true,\"readFromDocValues\":true},{\"name\":\"httpversion\",\"type\":\"string\",\"count\":0,\"scripted\":false,\"searchable\":true,\"aggregatable\":false,\"readFromDocValues\":false},{\"name\":\"httpversion.keyword\",\"type\":\"string\",\"count\":0,\"scripted\":false,\"searchable\":true,\"aggregatable\":true,\"readFromDocValues\":true},{\"name\":\"ident\",\"type\":\"string\",\"count\":0,\"scripted\":false,\"searchable\":true,\"aggregatable\":false,\"readFromDocValues\":false},{\"name\":\"ident.keyword\",\"type\":\"string\",\"count\":0,\"scripted\":false,\"searchable\":true,\"aggregatable\":true,\"readFromDocValues\":true},{\"name\":\"input.type\",\"type\":\"string\",\"count\":0,\"scripted\":false,\"searchable\":true,\"aggregatable\":false,\"readFromDocValues\":false},{\"name\":\"input.type.keyword\",\"type\":\"string\",\"count\":0,\"scripted\":false,\"searchable\":true,\"aggregatable\":true,\"readFromDocValues\":true},{\"name\":\"major\",\"type\":\"string\",\"count\":0,\"scripted\":false,\"searchable\":true,\"aggregatable\":false,\"readFromDocValues\":false},{\"name\":\"major.keyword\",\"type\":\"string\",\"count\":0,\"scripted\":false,\"searchable\":true,\"aggregatable\":true,\"readFromDocValues\":true},{\"name\":\"message\",\"type\":\"string\",\"count\":0,\"scripted\":false,\"searchable\":true,\"aggregatable\":false,\"readFromDocValues\":false},{\"name\":\"message.keyword\",\"type\":\"string\",\"count\":0,\"scripted\":false,\"searchable\":true,\"aggregatable\":true,\"readFromDocValues\":true},{\"name\":\"minor\",\"type\":\"string\",\"count\":0,\"scripted\":false,\"searchable\":true,\"aggregatable\":false,\"readFromDocValues\":false},{\"name\":\"minor.keyword\",\"type\":\"string\",\"count\":0,\"scripted\":false,\"searchable\":true,\"aggregatable\":true,\"readFromDocValues\":true},{\"name\":\"name\",\"type\":\"string\",\"count\":0,\"scripted\":false,\"searchable\":true,\"aggregatable\":false,\"readFromDocValues\":false},{\"name\":\"name.keyword\",\"type\":\"string\",\"count\":0,\"scripted\":false,\"searchable\":true,\"aggregatable\":true,\"readFromDocValues\":true},{\"name\":\"offset\",\"type\":\"number\",\"count\":0,\"scripted\":false,\"searchable\":true,\"aggregatable\":true,\"readFromDocValues\":true},{\"name\":\"os\",\"type\":\"string\",\"count\":0,\"scripted\":false,\"searchable\":true,\"aggregatable\":false,\"readFromDocValues\":false},{\"name\":\"os.keyword\",\"type\":\"string\",\"count\":0,\"scripted\":false,\"searchable\":true,\"aggregatable\":true,\"readFromDocValues\":true},{\"name\":\"os_major\",\"type\":\"string\",\"count\":0,\"scripted\":false,\"searchable\":true,\"aggregatable\":false,\"readFromDocValues\":false},{\"name\":\"os_major.keyword\",\"type\":\"string\",\"count\":0,\"scripted\":false,\"searchable\":true,\"aggregatable\":true,\"readFromDocValues\":true},{\"name\":\"os_minor\",\"type\":\"string\",\"count\":0,\"scripted\":false,\"searchable\":true,\"aggregatable\":false,\"readFromDocValues\":false},{\"name\":\"os_minor.keyword\",\"type\":\"string\",\"count\":0,\"scripted\":false,\"searchable\":true,\"aggregatable\":true,\"readFromDocValues\":true},{\"name\":\"os_name\",\"type\":\"string\",\"count\":0,\"scripted\":false,\"searchable\":true,\"aggregatable\":false,\"readFromDocValues\":false},{\"name\":\"os_name.keyword\",\"type\":\"string\",\"count\":0,\"scripted\":false,\"searchable\":true,\"aggregatable\":true,\"readFromDocValues\":true},{\"name\":\"patch\",\"type\":\"string\",\"count\":0,\"scripted\":false,\"searchable\":true,\"aggregatable\":false,\"readFromDocValues\":false},{\"name\":\"patch.keyword\",\"type\":\"string\",\"count\":0,\"scripted\":false,\"searchable\":true,\"aggregatable\":true,\"readFromDocValues\":true},{\"name\":\"prospector.type\",\"type\":\"string\",\"count\":0,\"scripted\":false,\"searchable\":true,\"aggregatable\":false,\"readFromDocValues\":false},{\"name\":\"prospector.type.keyword\",\"type\":\"string\",\"count\":0,\"scripted\":false,\"searchable\":true,\"aggregatable\":true,\"readFromDocValues\":true},{\"name\":\"referrer\",\"type\":\"string\",\"count\":0,\"scripted\":false,\"searchable\":true,\"aggregatable\":false,\"readFromDocValues\":false},{\"name\":\"referrer.keyword\",\"type\":\"string\",\"count\":0,\"scripted\":false,\"searchable\":true,\"aggregatable\":true,\"readFromDocValues\":true},{\"name\":\"request\",\"type\":\"string\",\"count\":0,\"scripted\":false,\"searchable\":true,\"aggregatable\":false,\"readFromDocValues\":false},{\"name\":\"request.keyword\",\"type\":\"string\",\"count\":0,\"scripted\":false,\"searchable\":true,\"aggregatable\":true,\"readFromDocValues\":true},{\"name\":\"response\",\"type\":\"string\",\"count\":0,\"scripted\":false,\"searchable\":true,\"aggregatable\":false,\"readFromDocValues\":false},{\"name\":\"response.keyword\",\"type\":\"string\",\"count\":0,\"scripted\":false,\"searchable\":true,\"aggregatable\":true,\"readFromDocValues\":true},{\"name\":\"source\",\"type\":\"string\",\"count\":0,\"scripted\":false,\"searchable\":true,\"aggregatable\":false,\"readFromDocValues\":false},{\"name\":\"source.keyword\",\"type\":\"string\",\"count\":0,\"scripted\":false,\"searchable\":true,\"aggregatable\":true,\"readFromDocValues\":true},{\"name\":\"swagger.operationid\",\"type\":\"string\",\"count\":0,\"scripted\":false,\"searchable\":true,\"aggregatable\":false,\"readFromDocValues\":false},{\"name\":\"swagger.operationid.keyword\",\"type\":\"string\",\"count\":0,\"scripted\":false,\"searchable\":true,\"aggregatable\":true,\"readFromDocValues\":true},{\"name\":\"swagger.tag\",\"type\":\"string\",\"count\":0,\"scripted\":false,\"searchable\":true,\"aggregatable\":false,\"readFromDocValues\":false},{\"name\":\"swagger.tag.keyword\",\"type\":\"string\",\"count\":0,\"scripted\":false,\"searchable\":true,\"aggregatable\":true,\"readFromDocValues\":true},{\"name\":\"tags\",\"type\":\"string\",\"count\":0,\"scripted\":false,\"searchable\":true,\"aggregatable\":false,\"readFromDocValues\":false},{\"name\":\"tags.keyword\",\"type\":\"string\",\"count\":0,\"scripted\":false,\"searchable\":true,\"aggregatable\":true,\"readFromDocValues\":true},{\"name\":\"timestamp\",\"type\":\"string\",\"count\":0,\"scripted\":false,\"searchable\":true,\"aggregatable\":false,\"readFromDocValues\":false},{\"name\":\"timestamp.keyword\",\"type\":\"string\",\"count\":0,\"scripted\":false,\"searchable\":true,\"aggregatable\":true,\"readFromDocValues\":true},{\"name\":\"verb\",\"type\":\"string\",\"count\":0,\"scripted\":false,\"searchable\":true,\"aggregatable\":false,\"readFromDocValues\":false},{\"name\":\"verb.keyword\",\"type\":\"string\",\"count\":0,\"scripted\":false,\"searchable\":true,\"aggregatable\":true,\"readFromDocValues\":true},{\"name\":\"hourOfDay\",\"type\":\"number\",\"count\":0,\"scripted\":true,\"script\":\"doc['@timestamp'].date.hourOfDay\",\"lang\":\"painless\",\"searchable\":true,\"aggregatable\":true,\"readFromDocValues\":false},{\"name\":\"dayOfWeek\",\"type\":\"number\",\"count\":0,\"scripted\":true,\"script\":\"doc['@timestamp'].date.dayOfWeek\",\"lang\":\"painless\",\"searchable\":true,\"aggregatable\":true,\"readFromDocValues\":false}]",
      "fieldFormatMap": "{\"hourOfDay\":{},\"dayOfWeek\":{}}"
    },
    "_meta": {
      "savedObjectVersion": 2
    }
  },
  {
    "_id": "ab3c0b80-e8af-11e8-9114-5703bc5a3337",
    "_type": "visualization",
    "_source": {
      "title": "petstore - heatmap per country",
      "visState": "{\"title\":\"petstore - heatmap per country\",\"type\":\"region_map\",\"params\":{\"legendPosition\":\"bottomright\",\"addTooltip\":true,\"colorSchema\":\"Blues\",\"selectedLayer\":{\"attribution\":\"<p><a href=\\\"http://www.naturalearthdata.com/about/terms-of-use\\\">Made with NaturalEarth</a>|<a href=\\\"https://www.elastic.co/elastic-maps-service\\\">Elastic Maps Service</a></p>&#10;\",\"weight\":1,\"name\":\"World Countries\",\"url\":\"https://vector.maps.elastic.co/blob/5659313586569216?elastic_tile_service_tos=agree&my_app_version=6.4.3&license=9afff109-304c-4f0c-bbaf-99d4ebb52a55\",\"format\":{\"type\":\"geojson\"},\"fields\":[{\"name\":\"iso2\",\"description\":\"Two letter abbreviation\"},{\"name\":\"name\",\"description\":\"Country name\"},{\"name\":\"iso3\",\"description\":\"Three letter abbreviation\"}],\"created_at\":\"2017-04-26T17:12:15.978370\",\"tags\":[],\"id\":5659313586569216,\"layerId\":\"elastic_maps_service.World Countries\",\"isEMS\":true},\"emsHotLink\":\"https://maps.elastic.co/v2#file/World Countries\",\"selectedJoinField\":{\"name\":\"iso2\",\"description\":\"Two letter abbreviation\"},\"isDisplayWarning\":true,\"wms\":{\"enabled\":false,\"options\":{\"format\":\"image/png\",\"transparent\":true},\"baseLayersAreLoaded\":{},\"tmsLayers\":[{\"id\":\"road_map\",\"url\":\"https://tiles.maps.elastic.co/v2/default/{z}/{x}/{y}.png?elastic_tile_service_tos=agree&my_app_name=kibana&my_app_version=6.4.3&license=9afff109-304c-4f0c-bbaf-99d4ebb52a55\",\"minZoom\":0,\"maxZoom\":18,\"attribution\":\"<p>&#169; <a href=\\\"http://www.openstreetmap.org/copyright\\\">OpenStreetMap</a> contributors | <a href=\\\"https://www.elastic.co/elastic-maps-service\\\">Elastic Maps Service</a></p>&#10;\",\"subdomains\":[]}],\"selectedTmsLayer\":{\"id\":\"road_map\",\"url\":\"https://tiles.maps.elastic.co/v2/default/{z}/{x}/{y}.png?elastic_tile_service_tos=agree&my_app_name=kibana&my_app_version=6.4.3&license=9afff109-304c-4f0c-bbaf-99d4ebb52a55\",\"minZoom\":0,\"maxZoom\":18,\"attribution\":\"<p>&#169; <a href=\\\"http://www.openstreetmap.org/copyright\\\">OpenStreetMap</a> contributors | <a href=\\\"https://www.elastic.co/elastic-maps-service\\\">Elastic Maps Service</a></p>&#10;\",\"subdomains\":[]}},\"mapZoom\":2,\"mapCenter\":[0,0],\"outlineWeight\":1,\"showAllShapes\":true},\"aggs\":[{\"id\":\"1\",\"enabled\":true,\"type\":\"count\",\"schema\":\"metric\",\"params\":{}},{\"id\":\"2\",\"enabled\":true,\"type\":\"terms\",\"schema\":\"segment\",\"params\":{\"field\":\"geoip.country_code2.keyword\",\"size\":1000,\"order\":\"desc\",\"orderBy\":\"1\",\"otherBucket\":false,\"otherBucketLabel\":\"Other\",\"missingBucket\":false,\"missingBucketLabel\":\"Missing\"}}]}",
      "uiStateJSON": "{\"mapZoom\":2,\"mapCenter\":[14.774882506516272,-6.679687500000001]}",
      "description": "",
      "version": 1,
      "kibanaSavedObjectMeta": {
        "searchSourceJSON": "{\"index\":\"93051120-e8a9-11e8-a41c-f3af534e2a1b\",\"query\":{\"query\":\"\",\"language\":\"lucene\"},\"filter\":[]}"
      }
    },
    "_meta": {
      "savedObjectVersion": 2
    }
  },
  {
    "_id": "478305d0-e8af-11e8-9114-5703bc5a3337",
    "_type": "visualization",
    "_source": {
      "title": "petstore - access map",
      "visState": "{\"title\":\"petstore - access map\",\"type\":\"tile_map\",\"params\":{\"colorSchema\":\"Yellow to Red\",\"mapType\":\"Scaled Circle Markers\",\"isDesaturated\":true,\"addTooltip\":true,\"heatClusterSize\":1.5,\"legendPosition\":\"bottomright\",\"mapZoom\":2,\"mapCenter\":[0,0],\"wms\":{\"enabled\":false,\"options\":{\"format\":\"image/png\",\"transparent\":true},\"baseLayersAreLoaded\":{},\"tmsLayers\":[{\"id\":\"road_map\",\"url\":\"https://tiles.maps.elastic.co/v2/default/{z}/{x}/{y}.png?elastic_tile_service_tos=agree&my_app_name=kibana&my_app_version=6.4.3&license=9afff109-304c-4f0c-bbaf-99d4ebb52a55\",\"minZoom\":0,\"maxZoom\":18,\"attribution\":\"<p>&#169; <a href=\\\"http://www.openstreetmap.org/copyright\\\">OpenStreetMap</a> contributors | <a href=\\\"https://www.elastic.co/elastic-maps-service\\\">Elastic Maps Service</a></p>&#10;\",\"subdomains\":[]}],\"selectedTmsLayer\":{\"id\":\"road_map\",\"url\":\"https://tiles.maps.elastic.co/v2/default/{z}/{x}/{y}.png?elastic_tile_service_tos=agree&my_app_name=kibana&my_app_version=6.4.3&license=9afff109-304c-4f0c-bbaf-99d4ebb52a55\",\"minZoom\":0,\"maxZoom\":18,\"attribution\":\"<p>&#169; <a href=\\\"http://www.openstreetmap.org/copyright\\\">OpenStreetMap</a> contributors | <a href=\\\"https://www.elastic.co/elastic-maps-service\\\">Elastic Maps Service</a></p>&#10;\",\"subdomains\":[]}}},\"aggs\":[{\"id\":\"1\",\"enabled\":true,\"type\":\"count\",\"schema\":\"metric\",\"params\":{}},{\"id\":\"2\",\"enabled\":true,\"type\":\"geohash_grid\",\"schema\":\"segment\",\"params\":{\"field\":\"geoip.location\",\"autoPrecision\":true,\"isFilteredByCollar\":true,\"useGeocentroid\":true,\"mapZoom\":4,\"mapCenter\":{\"lon\":-89.64843750000001,\"lat\":14.732386081418454},\"precision\":2}}]}",
      "uiStateJSON": "{\"mapZoom\":3,\"mapCenter\":[41.046216814520655,-88.06640625000001]}",
      "description": "",
      "version": 1,
      "kibanaSavedObjectMeta": {
        "searchSourceJSON": "{\"index\":\"93051120-e8a9-11e8-a41c-f3af534e2a1b\",\"query\":{\"query\":\"\",\"language\":\"lucene\"},\"filter\":[]}"
      }
    },
    "_meta": {
      "savedObjectVersion": 2
    }
  },
  {
    "_id": "916aabf0-e8b2-11e8-9114-5703bc5a3337",
    "_type": "visualization",
    "_source": {
      "title": "petstore - top operation",
      "visState": "{\"title\":\"petstore - top operation\",\"type\":\"horizontal_bar\",\"params\":{\"type\":\"histogram\",\"grid\":{\"categoryLines\":false,\"style\":{\"color\":\"#eee\"}},\"categoryAxes\":[{\"id\":\"CategoryAxis-1\",\"type\":\"category\",\"position\":\"left\",\"show\":true,\"style\":{},\"scale\":{\"type\":\"linear\"},\"labels\":{\"show\":true,\"rotate\":0,\"filter\":false,\"truncate\":200},\"title\":{}}],\"valueAxes\":[{\"id\":\"ValueAxis-1\",\"name\":\"LeftAxis-1\",\"type\":\"value\",\"position\":\"bottom\",\"show\":true,\"style\":{},\"scale\":{\"type\":\"linear\",\"mode\":\"normal\"},\"labels\":{\"show\":true,\"rotate\":75,\"filter\":true,\"truncate\":100},\"title\":{\"text\":\"Count\"}}],\"seriesParams\":[{\"show\":true,\"type\":\"histogram\",\"mode\":\"normal\",\"data\":{\"label\":\"Count\",\"id\":\"1\"},\"valueAxis\":\"ValueAxis-1\",\"drawLinesBetweenPoints\":true,\"showCircles\":true}],\"addTooltip\":true,\"addLegend\":true,\"legendPosition\":\"right\",\"times\":[],\"addTimeMarker\":false},\"aggs\":[{\"id\":\"1\",\"enabled\":true,\"type\":\"count\",\"schema\":\"metric\",\"params\":{}},{\"id\":\"2\",\"enabled\":true,\"type\":\"significant_terms\",\"schema\":\"segment\",\"params\":{\"field\":\"swagger.operationid.keyword\",\"size\":20}}]}",
      "uiStateJSON": "{\"vis\":{\"colors\":{\"Count\":\"#0A50A1\"}}}",
      "description": "",
      "version": 1,
      "kibanaSavedObjectMeta": {
        "searchSourceJSON": "{\"index\":\"93051120-e8a9-11e8-a41c-f3af534e2a1b\",\"query\":{\"query\":\"\",\"language\":\"lucene\"},\"filter\":[]}"
      }
    },
    "_meta": {
      "savedObjectVersion": 2
    }
  },
  {
    "_id": "8e320110-e8b0-11e8-9114-5703bc5a3337",
    "_type": "visualization",
    "_source": {
      "title": "petstore - weekly heatmap",
      "visState": "{\"title\":\"petstore - weekly heatmap\",\"type\":\"heatmap\",\"params\":{\"type\":\"heatmap\",\"addTooltip\":true,\"addLegend\":true,\"enableHover\":false,\"legendPosition\":\"right\",\"times\":[],\"colorsNumber\":4,\"colorSchema\":\"Blues\",\"setColorRange\":false,\"colorsRange\":[],\"invertColors\":false,\"percentageMode\":false,\"valueAxes\":[{\"show\":false,\"id\":\"ValueAxis-1\",\"type\":\"value\",\"scale\":{\"type\":\"linear\",\"defaultYExtents\":false},\"labels\":{\"show\":false,\"rotate\":0,\"overwriteColor\":false,\"color\":\"#555\"}}]},\"aggs\":[{\"id\":\"1\",\"enabled\":true,\"type\":\"count\",\"schema\":\"metric\",\"params\":{}},{\"id\":\"2\",\"enabled\":true,\"type\":\"histogram\",\"schema\":\"segment\",\"params\":{\"field\":\"dayOfWeek\",\"interval\":1,\"min_doc_count\":true,\"extended_bounds\":{\"min\":1,\"max\":7}}},{\"id\":\"3\",\"enabled\":true,\"type\":\"histogram\",\"schema\":\"group\",\"params\":{\"field\":\"hourOfDay\",\"interval\":1,\"min_doc_count\":true,\"extended_bounds\":{\"min\":0,\"max\":23}}}]}",
      "uiStateJSON": "{\"vis\":{\"defaultColors\":{\"0 - 13\":\"rgb(247,251,255)\",\"13 - 25\":\"rgb(198,219,239)\",\"25 - 38\":\"rgb(107,174,214)\",\"38 - 50\":\"rgb(33,113,181)\"}}}",
      "description": "",
      "version": 1,
      "kibanaSavedObjectMeta": {
        "searchSourceJSON": "{\"index\":\"93051120-e8a9-11e8-a41c-f3af534e2a1b\",\"query\":{\"query\":\"\",\"language\":\"lucene\"},\"filter\":[]}"
      }
    },
    "_meta": {
      "savedObjectVersion": 2
    }
  },
  {
    "_id": "e7516ea0-e8ad-11e8-9114-5703bc5a3337",
    "_type": "visualization",
    "_source": {
      "title": "petstore - access by country",
      "visState": "{\"title\":\"petstore - access by country\",\"type\":\"pie\",\"params\":{\"type\":\"pie\",\"addTooltip\":true,\"addLegend\":true,\"legendPosition\":\"right\",\"isDonut\":true,\"labels\":{\"show\":false,\"values\":true,\"last_level\":true,\"truncate\":100}},\"aggs\":[{\"id\":\"1\",\"enabled\":true,\"type\":\"count\",\"schema\":\"metric\",\"params\":{}},{\"id\":\"2\",\"enabled\":true,\"type\":\"terms\",\"schema\":\"segment\",\"params\":{\"field\":\"geoip.country_name.keyword\",\"size\":20,\"order\":\"desc\",\"orderBy\":\"1\",\"otherBucket\":false,\"otherBucketLabel\":\"Other\",\"missingBucket\":false,\"missingBucketLabel\":\"Missing\"}}]}",
      "uiStateJSON": "{}",
      "description": "",
      "version": 1,
      "kibanaSavedObjectMeta": {
        "searchSourceJSON": "{\"index\":\"93051120-e8a9-11e8-a41c-f3af534e2a1b\",\"query\":{\"query\":\"\",\"language\":\"lucene\"},\"filter\":[]}"
      }
    },
    "_meta": {
      "savedObjectVersion": 2
    }
  },
  {
    "_id": "27d7fca0-e8ae-11e8-9114-5703bc5a3337",
    "_type": "visualization",
    "_source": {
      "title": "petstore - access by browser",
      "visState": "{\"title\":\"petstore - access by browser\",\"type\":\"pie\",\"params\":{\"type\":\"pie\",\"addTooltip\":true,\"addLegend\":true,\"legendPosition\":\"right\",\"isDonut\":false,\"labels\":{\"show\":false,\"values\":true,\"last_level\":true,\"truncate\":100}},\"aggs\":[{\"id\":\"1\",\"enabled\":true,\"type\":\"count\",\"schema\":\"metric\",\"params\":{}},{\"id\":\"2\",\"enabled\":true,\"type\":\"terms\",\"schema\":\"segment\",\"params\":{\"field\":\"name.keyword\",\"size\":5,\"order\":\"desc\",\"orderBy\":\"1\",\"otherBucket\":false,\"otherBucketLabel\":\"Other\",\"missingBucket\":false,\"missingBucketLabel\":\"Missing\"}}]}",
      "uiStateJSON": "{}",
      "description": "",
      "version": 1,
      "kibanaSavedObjectMeta": {
        "searchSourceJSON": "{\"index\":\"93051120-e8a9-11e8-a41c-f3af534e2a1b\",\"query\":{\"query\":\"\",\"language\":\"lucene\"},\"filter\":[]}"
      }
    },
    "_meta": {
      "savedObjectVersion": 2
    }
  },
  {
    "_id": "1e2d0d70-e8af-11e8-9114-5703bc5a3337",
    "_type": "visualization",
    "_source": {
      "title": "petstore - access by verb",
      "visState": "{\"title\":\"petstore - access by verb\",\"type\":\"pie\",\"params\":{\"type\":\"pie\",\"addTooltip\":true,\"addLegend\":true,\"legendPosition\":\"right\",\"isDonut\":true,\"labels\":{\"show\":false,\"values\":true,\"last_level\":true,\"truncate\":100}},\"aggs\":[{\"id\":\"1\",\"enabled\":true,\"type\":\"count\",\"schema\":\"metric\",\"params\":{}},{\"id\":\"2\",\"enabled\":true,\"type\":\"terms\",\"schema\":\"segment\",\"params\":{\"field\":\"verb.keyword\",\"size\":8,\"order\":\"desc\",\"orderBy\":\"1\",\"otherBucket\":false,\"otherBucketLabel\":\"Other\",\"missingBucket\":false,\"missingBucketLabel\":\"Missing\"}}]}",
      "uiStateJSON": "{}",
      "description": "",
      "version": 1,
      "kibanaSavedObjectMeta": {
        "searchSourceJSON": "{\"index\":\"93051120-e8a9-11e8-a41c-f3af534e2a1b\",\"query\":{\"query\":\"\",\"language\":\"lucene\"},\"filter\":[]}"
      }
    },
    "_meta": {
      "savedObjectVersion": 2
    }
  },
  {
    "_id": "c20c1fb0-e8b1-11e8-9114-5703bc5a3337",
    "_type": "visualization",
    "_source": {
      "title": "petstore - timeline per http status",
      "visState": "{\"title\":\"petstore - timeline per http status\",\"type\":\"timelion\",\"params\":{\"expression\":\".es(index=petstore-*, split=response.keyword:10).bars().label(\\\"$1 status\\\",\\\".*(\\\\d{3}).*\\\")\",\"interval\":\"auto\"},\"aggs\":[]}",
      "uiStateJSON": "{}",
      "description": "",
      "version": 1,
      "kibanaSavedObjectMeta": {
        "searchSourceJSON": "{\"query\":{\"query\":\"\",\"language\":\"lucene\"},\"filter\":[]}"
      }
    },
    "_meta": {
      "savedObjectVersion": 2
    }
  },
  {
    "_id": "674efd20-e8b3-11e8-9114-5703bc5a3337",
    "_type": "dashboard",
    "_source": {
      "title": "petstore - dashboard",
      "hits": 0,
      "description": "",
      "panelsJSON": "[{\"embeddableConfig\":{\"mapCenter\":[37.30027528134433,-99.31640625000001],\"mapZoom\":3},\"gridData\":{\"h\":18,\"i\":\"2\",\"w\":31,\"x\":0,\"y\":10},\"id\":\"478305d0-e8af-11e8-9114-5703bc5a3337\",\"panelIndex\":\"2\",\"type\":\"visualization\",\"version\":\"6.4.3\"},{\"embeddableConfig\":{\"vis\":{\"colors\":{\"Count\":\"#0A50A1\"},\"legendOpen\":false}},\"gridData\":{\"h\":16,\"i\":\"3\",\"w\":16,\"x\":0,\"y\":28},\"id\":\"916aabf0-e8b2-11e8-9114-5703bc5a3337\",\"panelIndex\":\"3\",\"type\":\"visualization\",\"version\":\"6.4.3\"},{\"embeddableConfig\":{\"vis\":{\"defaultColors\":{\"0 - 13\":\"rgb(247,251,255)\",\"13 - 25\":\"rgb(198,219,239)\",\"25 - 38\":\"rgb(107,174,214)\",\"38 - 50\":\"rgb(33,113,181)\"},\"legendOpen\":false}},\"gridData\":{\"h\":18,\"i\":\"4\",\"w\":17,\"x\":31,\"y\":44},\"id\":\"8e320110-e8b0-11e8-9114-5703bc5a3337\",\"panelIndex\":\"4\",\"type\":\"visualization\",\"version\":\"6.4.3\"},{\"embeddableConfig\":{},\"gridData\":{\"h\":18,\"i\":\"5\",\"w\":17,\"x\":31,\"y\":10},\"id\":\"e7516ea0-e8ad-11e8-9114-5703bc5a3337\",\"panelIndex\":\"5\",\"type\":\"visualization\",\"version\":\"6.4.3\"},{\"embeddableConfig\":{},\"gridData\":{\"h\":16,\"i\":\"6\",\"w\":15,\"x\":16,\"y\":28},\"id\":\"27d7fca0-e8ae-11e8-9114-5703bc5a3337\",\"panelIndex\":\"6\",\"type\":\"visualization\",\"version\":\"6.4.3\"},{\"embeddableConfig\":{},\"gridData\":{\"h\":16,\"i\":\"7\",\"w\":17,\"x\":31,\"y\":28},\"id\":\"1e2d0d70-e8af-11e8-9114-5703bc5a3337\",\"panelIndex\":\"7\",\"type\":\"visualization\",\"version\":\"6.4.3\"},{\"embeddableConfig\":{},\"gridData\":{\"h\":10,\"i\":\"8\",\"w\":48,\"x\":0,\"y\":0},\"id\":\"c20c1fb0-e8b1-11e8-9114-5703bc5a3337\",\"panelIndex\":\"8\",\"type\":\"visualization\",\"version\":\"6.4.3\"}]",
      "optionsJSON": "{\"darkTheme\":false,\"hidePanelTitles\":false,\"useMargins\":false}",
      "version": 1,
      "timeRestore": false,
      "kibanaSavedObjectMeta": {
        "searchSourceJSON": "{\"query\":{\"language\":\"lucene\",\"query\":\"\"},\"filter\":[]}"
      }
    },
    "_meta": {
      "savedObjectVersion": 2
    }
  },
  {
    "_id": "d7966d70-e8b3-11e8-9114-5703bc5a3337",
    "_type": "visualization",
    "_source": {
      "title": "petstore - significant urls",
      "visState": "{\"title\":\"petstore - significant urls\",\"type\":\"table\",\"params\":{\"perPage\":10,\"showPartialRows\":false,\"showMetricsAtAllLevels\":false,\"sort\":{\"columnIndex\":null,\"direction\":null},\"showTotal\":false,\"totalFunc\":\"sum\"},\"aggs\":[{\"id\":\"1\",\"enabled\":true,\"type\":\"count\",\"schema\":\"metric\",\"params\":{}},{\"id\":\"2\",\"enabled\":true,\"type\":\"terms\",\"schema\":\"bucket\",\"params\":{\"field\":\"httprequest.keyword\",\"size\":50,\"order\":\"desc\",\"orderBy\":\"1\",\"otherBucket\":false,\"otherBucketLabel\":\"Other\",\"missingBucket\":false,\"missingBucketLabel\":\"Missing\",\"customLabel\":\"Http Request\"}}]}",
      "uiStateJSON": "{\"vis\":{\"params\":{\"sort\":{\"columnIndex\":null,\"direction\":null}}}}",
      "description": "",
      "version": 1,
      "kibanaSavedObjectMeta": {
        "searchSourceJSON": "{\"index\":\"93051120-e8a9-11e8-a41c-f3af534e2a1b\",\"query\":{\"query\":\"\",\"language\":\"lucene\"},\"filter\":[]}"
      }
    },
    "_meta": {
      "savedObjectVersion": 2
    }
  }
]